remotecodes/__init__.py
remotecodes/__main__.py
remotecodes/py.typed
remotecodes/schema/__init__.py
remotecodes/schema/common.py
remotecodes/schema/media_player.py
remotecodes-0.0.1.dist-info/METADATA
remotecodes-0.0.1.dist-info/WHEEL
remotecodes-0.0.1.dist-info/top_level.txt
remotecodes-0.0.1.dist-info/RECORD
