Metadata-Version: 2.1
Name: remotecodes
Version: 0.0.1
Summary: Structured and validated IR / RF remote codes for many devices
Home-page: https://github.com/ianchi/remotecodes
Author: Adrian Panella
Author-email: ianchi74@outlook.com
License: MIT
Project-URL: Bug Tracker, https://github.com/ianchi/remotecodes/issues
Platform: UNKNOWN
Classifier: Programming Language :: Python :: 3
Classifier: License :: OSI Approved :: MIT License
Classifier: Operating System :: OS Independent
Classifier: Topic :: Software Development :: Embedded Systems
Classifier: Topic :: Home Automation
Requires-Python: >=3.8
Requires-Dist: voluptuous (<0.13,>=0.12.2)
Requires-Dist: remoteprotocols (>=0.0.5)
